attendant/__init__.py
attendant/__main__.py
attendant/cli.py
attendant/configuration.py
attendant/mailNotify.py
attendant/mailnotify.py
attendant/validation.py
attendant-0.1.2.dist-info/DESCRIPTION.rst
attendant-0.1.2.dist-info/METADATA
attendant-0.1.2.dist-info/RECORD
attendant-0.1.2.dist-info/WHEEL
attendant-0.1.2.dist-info/entry_points.txt
attendant-0.1.2.dist-info/metadata.json
attendant-0.1.2.dist-info/top_level.txt
